<?xml version="1.0" encoding="UTF-8" standalone="yes"?>
<catalog xmlns:xi="http://www.w3.org/2001/XInclude" xmlns:xsi="http://www.w3.org/2001/XMLSchema-instance" code="blackListEmails" seg-detach="true" seg-id="blackListEmails" seg-type="catalog" xsi:type="SystemCatalog">
    <title lang="client">Черный список отправителей письма</title>
    <title lang="en">Blacklist of e-mail senders</title>
    <title lang="ru">Черный список отправителей письма</title>
    <description lang="client">Cодержит список адресов отправителей, письма с которых не подлежат обработке.</description>
    <description lang="en">Contains list of e-mail senders to prevent mail processing.</description>
    <description lang="ru">Cодержит список адресов отправителей, письма с которых не подлежат обработке.</description>
</catalog>
