<?xml version="1.0" encoding="UTF-8" standalone="yes"?>
<action xmlns:xi="http://www.w3.org/2001/XInclude" seg-detach="true" seg-id="showAdvlistFilter_ad355904-b5d9-fe8a-a96c-8d361a93e64e" seg-type="tools" uuid="ad355904-b5d9-fe8a-a96c-8d361a93e64e">
    <profiles/>
    <tags/>
    <appliedToType>currentObject</appliedToType>
    <params/>
    <presentationType>push</presentationType>
    <action>showAdvlistFilter</action>
    <allowedInMassOperations>true</allowedInMassOperations>
    <blockable>true</blockable>
    <caption lang="en">Filtration</caption>
    <caption lang="ru">Фильтрация...</caption>
</action>
