<?xml version="1.0" encoding="UTF-8" standalone="yes"?>
<toolPanel xmlns:xi="http://www.w3.org/2001/XInclude" seg-detach="true" seg-id="2d7a2afc-40d9-cd86-887e-c913314a780c" seg-type="tool-panels" uuid="2d7a2afc-40d9-cd86-887e-c913314a780c">
    <profiles/>
    <tags/>
    <ignoreInImport>false</ignoreInImport>
    <showToolCaptions>true</showToolCaptions>
    <toolBars seg-detach="false" uuid="f9ec76d5-15f0-48e2-0022-000001ded46d">
        <profiles/>
        <tags/>
        <clearedAfterPermissionCheck>false</clearedAfterPermissionCheck>
        <xi:include href="tools/addComment_f9ec76d5-15f0-48e3-0022-000001ded46d.xml" parse="xml"/>
    </toolBars>
    <useSystemSettings>false</useSystemSettings>
</toolPanel>
