<?xml version="1.0" encoding="UTF-8" standalone="yes"?>
<edit-form xmlns:xi="http://www.w3.org/2001/XInclude" seg-detach="true" seg-id="changeTask" seg-type="edit-forms" uuid="changeTask">
    <profiles>
        <profile>208d47ce-f713-4839-b89a-732682102b25</profile>
        <profile>c3878215-3a21-497d-a606-8854503ead1a</profile>
        <profile>3f6043f1-42df-45dd-a13f-12732c327b21</profile>
        <profile>862e093f-ff10-4dab-b6f2-036fcb8cc02d</profile>
        <profile>51da8cfb-cfd8-4507-95a0-5c47eae79976</profile>
    </profiles>
    <tags>
        <tag>Zadachi</tag>
    </tags>
    <cases/>
    <class>
        <id>task</id>
    </class>
    <attributes>
        <xi:include href="attributes/responsible.xml" parse="xml"/>
        <xi:include href="attributes/deadline.xml" parse="xml"/>
    </attributes>
</edit-form>
