<?xml version="1.0" encoding="UTF-8" standalone="yes"?>
<tabBar xmlns:xi="http://www.w3.org/2001/XInclude" hasHead="false" seg-detach="true" seg-id="f6af09c2-15a2-2452-0000-000001c8b871" seg-type="tab-bars" uuid="f6af09c2-15a2-2452-0000-000001c8b871">
    <profiles/>
    <tags/>
    <position>FULL</position>
    <visibilityCondition seg-detach="false" uuid="f1e8840a-1750-a963-0066-00007b344b54">
        <profiles/>
        <tags/>
    </visibilityCondition>
    <hideSingleTab>false</hideSingleTab>
    <tab additional="false" seg-detach="false" uuid="f6af09c2-15a2-2453-0000-000001c8b871">
        <profiles/>
        <tags/>
        <caption lang="en">Comment parameters</caption>
        <caption lang="ru">Параметры комментария</caption>
        <considerListFilter>false</considerListFilter>
        <xi:include href="tool-panels/f6af2982-15a2-7bf1-0000-000001c8b871.xml" parse="xml"/>
        <layout seg-detach="false" uuid="f6af09c2-15a2-2454-0000-000001c8b871">
            <profiles/>
            <tags/>
            <xi:include href="contents/f6af09c2-15a2-2455-0000-000001c8b871/f6af09c2-15a2-2455-0000-000001c8b871.xml" parse="xml"/>
            <xi:include href="contents/f6af09c2-15a2-2456-0000-000001c8b871/f6af09c2-15a2-2456-0000-000001c8b871.xml" parse="xml"/>
            <leftColumnWidth>60</leftColumnWidth>
            <windowLayout>false</windowLayout>
        </layout>
        <internalScrolling>INHERITED</internalScrolling>
        <visibilityCondition seg-detach="false" uuid="f1e8840b-1750-a966-0066-00007b344b54">
            <profiles/>
            <tags/>
        </visibilityCondition>
    </tab>
</tabBar>
